MoreBusServerLib/__init__.py
MoreBusServerLib/config.py
MoreBusServerLib/modloader.py
MoreBusServerLib/server.py
MoreBusServerLib/utils.py
morebus-0.1.0.dist-info/METADATA
morebus-0.1.0.dist-info/WHEEL
morebus-0.1.0.dist-info/top_level.txt
morebus-0.1.0.dist-info/RECORD
