Metadata-Version: 2.4
Name: morebus
Version: 0.1.0
Summary: Create A MoreBus Server from Python Library
Author: DevmevLp
Author-email: d7272581@gmail.com
Classifier: Programming Language :: Python :: 3
Classifier: Operating System :: OS Independent
Requires-Python: >=3.6
Dynamic: author
Dynamic: author-email
Dynamic: classifier
Dynamic: description-content-type
Dynamic: requires-python
Dynamic: summary
